scrapyd/VERSION
scrapyd/__init__.py
scrapyd/__main__.py
scrapyd/app.py
scrapyd/basicauth.py
scrapyd/config.py
scrapyd/default_scrapyd.conf
scrapyd/eggstorage.py
scrapyd/environ.py
scrapyd/exceptions.py
scrapyd/interfaces.py
scrapyd/jobstorage.py
scrapyd/launcher.py
scrapyd/poller.py
scrapyd/runner.py
scrapyd/scheduler.py
scrapyd/spiderqueue.py
scrapyd/sqlite.py
scrapyd/txapp.py
scrapyd/utils.py
scrapyd/webservice.py
scrapyd/website.py
scrapyd-1.5.0.dist-info/LICENSE
scrapyd-1.5.0.dist-info/METADATA
scrapyd-1.5.0.dist-info/WHEEL
scrapyd-1.5.0.dist-info/entry_points.txt
scrapyd-1.5.0.dist-info/top_level.txt
scrapyd-1.5.0.dist-info/RECORD
