Metadata-Version: 2.1
Name: scrapyd
Version: 1.5.0
Summary: A service for running Scrapy spiders, with an HTTP API
Home-page: https://github.com/scrapy/scrapyd
Author: Scrapy developers
Author-email: info@scrapy.org
License: BSD
Classifier: License :: OSI Approved :: BSD License
Classifier: Operating System :: OS Independent
Classifier: Programming Language :: Python
Classifier: Programming Language :: Python :: 3
Classifier: Programming Language :: Python :: 3.8
Classifier: Programming Language :: Python :: 3.9
Classifier: Programming Language :: Python :: 3.10
Classifier: Programming Language :: Python :: 3.11
Classifier: Programming Language :: Python :: 3.12
Classifier: Development Status :: 5 - Production/Stable
Classifier: Environment :: Console
Classifier: Environment :: No Input/Output (Daemon)
Classifier: Topic :: Internet :: WWW/HTTP
License-File: LICENSE
Requires-Dist: packaging
Requires-Dist: pywin32; platform_system == "Windows"
Requires-Dist: scrapy>=2.0.0
Requires-Dist: setuptools
Requires-Dist: twisted>=17.9
Requires-Dist: w3lib
Requires-Dist: zope.interface
Provides-Extra: test
Requires-Dist: coveralls; extra == "test"
Requires-Dist: py-html-checker; extra == "test"
Requires-Dist: pytest; extra == "test"
Requires-Dist: pytest-cov; extra == "test"
Requires-Dist: pytest-twisted; extra == "test"
Requires-Dist: requests; extra == "test"
Requires-Dist: twisted>=19.7; extra == "test"
Provides-Extra: docs
Requires-Dist: furo; extra == "docs"
Requires-Dist: sphinx; extra == "docs"
Requires-Dist: sphinx-autobuild; extra == "docs"
Requires-Dist: sphinxcontrib-zopeext; extra == "docs"
